humanize/__init__.py
humanize/filesize.py
humanize/i18n.py
humanize/number.py
humanize/py.typed
humanize/time.py
humanize/locale/ar/LC_MESSAGES/humanize.mo
humanize/locale/ar/LC_MESSAGES/humanize.po
humanize/locale/bn_BD/LC_MESSAGES/humanize.mo
humanize/locale/bn_BD/LC_MESSAGES/humanize.po
humanize/locale/ca_ES/LC_MESSAGES/humanize.mo
humanize/locale/ca_ES/LC_MESSAGES/humanize.po
humanize/locale/da_DK/LC_MESSAGES/humanize.mo
humanize/locale/da_DK/LC_MESSAGES/humanize.po
humanize/locale/de_DE/LC_MESSAGES/humanize.mo
humanize/locale/de_DE/LC_MESSAGES/humanize.po
humanize/locale/el_GR/LC_MESSAGES/humanize.mo
humanize/locale/el_GR/LC_MESSAGES/humanize.po
humanize/locale/es_ES/LC_MESSAGES/humanize.mo
humanize/locale/es_ES/LC_MESSAGES/humanize.po
humanize/locale/eu/LC_MESSAGES/humanize.mo
humanize/locale/eu/LC_MESSAGES/humanize.po
humanize/locale/fa_IR/LC_MESSAGES/humanize.mo
humanize/locale/fa_IR/LC_MESSAGES/humanize.po
humanize/locale/fi_FI/LC_MESSAGES/humanize.mo
humanize/locale/fi_FI/LC_MESSAGES/humanize.po
humanize/locale/fr_FR/LC_MESSAGES/humanize.mo
humanize/locale/fr_FR/LC_MESSAGES/humanize.po
humanize/locale/id_ID/LC_MESSAGES/humanize.mo
humanize/locale/id_ID/LC_MESSAGES/humanize.po
humanize/locale/it_IT/LC_MESSAGES/humanize.mo
humanize/locale/it_IT/LC_MESSAGES/humanize.po
humanize/locale/ja_JP/LC_MESSAGES/humanize.mo
humanize/locale/ja_JP/LC_MESSAGES/humanize.po
humanize/locale/ko_KR/LC_MESSAGES/humanize.mo
humanize/locale/ko_KR/LC_MESSAGES/humanize.po
humanize/locale/nl_NL/LC_MESSAGES/humanize.mo
humanize/locale/nl_NL/LC_MESSAGES/humanize.po
humanize/locale/pl_PL/LC_MESSAGES/humanize.mo
humanize/locale/pl_PL/LC_MESSAGES/humanize.po
humanize/locale/pt_BR/LC_MESSAGES/humanize.mo
humanize/locale/pt_BR/LC_MESSAGES/humanize.po
humanize/locale/pt_PT/LC_MESSAGES/humanize.mo
humanize/locale/pt_PT/LC_MESSAGES/humanize.po
humanize/locale/ru_RU/LC_MESSAGES/humanize.mo
humanize/locale/ru_RU/LC_MESSAGES/humanize.po
humanize/locale/sk_SK/LC_MESSAGES/humanize.mo
humanize-4.5.0.dist-info/LICENCE
humanize-4.5.0.dist-info/METADATA
humanize-4.5.0.dist-info/WHEEL
humanize-4.5.0.dist-info/top_level.txt
humanize-4.5.0.dist-info/RECORD
