Metadata-Version: 2.1
Name: humanize
Version: 4.5.0
Summary: Python humanize utilities
Author-email: Jason Moiron <jmoiron@jmoiron.net>
Maintainer: Hugo van Kemenade
License: MIT
Project-URL: Documentation, https://python-humanize.readthedocs.io/
Project-URL: Funding, https://tidelift.com/subscription/pkg/pypi-humanize?utm_source=pypi-humanize&utm_medium=pypi
Project-URL: Homepage, https://github.com/python-humanize/humanize
Project-URL: Issue tracker, https://github.com/python-humanize/humanize/issues
Project-URL: Release notes, https://github.com/python-humanize/humanize/releases
Project-URL: Source, https://github.com/python-humanize/humanize
Keywords: humanize time size
Classifier: Development Status :: 5 - Production/Stable
Classifier: Intended Audience :: Developers
Classifier: License :: OSI Approved :: MIT License
Classifier: Operating System :: OS Independent
Classifier: Programming Language :: Python
Classifier: Programming Language :: Python :: 3
Classifier: Programming Language :: Python :: 3 :: Only
Classifier: Programming Language :: Python :: 3.7
Classifier: Programming Language :: Python :: 3.8
Classifier: Programming Language :: Python :: 3.9
Classifier: Programming Language :: Python :: 3.10
Classifier: Programming Language :: Python :: 3.11
Classifier: Programming Language :: Python :: Implementation :: CPython
Classifier: Programming Language :: Python :: Implementation :: PyPy
Classifier: Topic :: Text Processing
Classifier: Topic :: Text Processing :: General
Requires-Python: >=3.7
Provides-Extra: tests
License-File: LICENCE
